{"sample_id": "Mockito_34", "model": "llama3-8b-groq", "code_context": "/*\n * Copyright (c) 2007 Mockito contributors\n * This program is made available under the terms of the MIT License.\n */\npackage org.mockito.internal.invocation;\n\nimport java.io.Serializable;\nimport java.lang.reflect.Method;\nimport java.util.Collections;\nimport java.util.List;\n\nimport org.hamcrest.Matcher;\nimport org.mockito.exceptions.PrintableInvocation;\nimport org.mockito.internal.debugging.Location;\nimport org.mockito.internal.matchers.CapturesArguments;\nimport org.mockito.internal.reporting.PrintSettings;\nimport org.mockito.internal.reporting.PrintingFriendlyInvocation;\n\n@SuppressWarnings(\"unchecked\")\npublic class InvocationMatcher implements PrintableInvocation, PrintingFriendlyInvocation, CapturesArgumensFromInvocation, Serializable {\n\n    private static final long serialVersionUID = -3047126096857467610L;\n    private final Invocation invocation;\n    private final List<Matcher> matchers;\n\n    public InvocationMatcher(Invocation invocation, List<Matcher> matchers) {\n        this.invocation = invocation;\n        if (matchers.isEmpty()) {\n            this.matchers = invocation.argumentsToMatchers();\n        } else {\n            this.matchers = matchers;\n        }\n    }\n    \n    public InvocationMatcher(Invocation invocation) {\n        this(invocation, Collections.<Matcher>emptyList());\n    }\n\n    public Method getMethod() {\n        return invocation.getMethod();\n    }\n    \n    public Invocation getInvocation() {\n        return this.invocation;\n    }\n    \n    public List<Matcher> getMatchers() {\n        return this.matchers;\n    }\n    \n    public String toString() {\n        return invocation.toString(matchers, new PrintSettings());\n    }\n\n    public boolean matches(Invocation actual) {\n        return invocation.getMock().equals(actual.getMock())\n                && hasSameMethod(actual)\n                && new ArgumentsComparator().argumentsMatch(this, actual);\n    }\n\n    private boolean safelyArgumentsMatch(Object[] actualArgs) {\n        try {\n            return new ArgumentsComparator().argumentsMatch(this, actualArgs);\n        } catch (Throwable t) {\n            return false;\n        }\n    }\n\n    /**\n     * similar means the same method name, same mock, unverified \n     * and: if arguments are the same cannot be overloaded\n     */\n    public boolean hasSimilarMethod(Invocation candidate) {\n        String wantedMethodName = getMethod().getName();\n        String currentMethodName = candidate.getMethod().getName();\n        \n        final boolean methodNameEquals = wantedMethodName.equals(currentMethodName);\n        final boolean isUnverified = !candidate.isVerified();\n        final boolean mockIsTheSame = getInvocation().getMock() == candidate.getMock();\n        final boolean methodEquals = hasSameMethod(candidate);\n\n        if (!methodNameEquals || !isUnverified || !mockIsTheSame) {\n            return false;\n        }\n\n        final boolean overloadedButSameArgs = !methodEquals && safelyArgumentsMatch(candidate.getArguments());\n\n        return !overloadedButSameArgs;\n    }\n\n    public boolean hasSameMethod(Invocation candidate) {\n        return invocation.getMethod().equals(candidate.getMethod());\n    }\n    \n    public Location getLocation() {\n        return invocation.getLocation();\n    }\n\n    public String toString(PrintSettings printSettings) {\n        return invocation.toString(matchers, printSettings);\n    }\n\n    public void captureArgumentsFrom(Invocation i) {\n        int k = 0;\n        for (Matcher m : matchers) {\n            if (m instanceof CapturesArguments) {\n                ((CapturesArguments) m).captureFrom(i.getArguments()[k]);\n            }\n            k++;\n        }\n    }\n}", "review": {"response": "{\n  \"bugs\": [\n      {\n         \"message\": \"Missing import statement for org.mockito.internal.invocation.Invocation\",\n         \"line\": 12,\n         \"column\": 13\n      },\n      {\n         \"message\": \"Missing import statement for org.mockito.internal.invocation.Invocation\",\n         \"line\": 33,\n         \"column\": 13\n      },\n      {\n         \"message\": \"Missing import statement for org.mockito.internal.invocation.Invocation\",\n         \"line\": 44,\n         \"column\": 13\n      },\n      {\n         \"message\": \"Missing import statement for org.mockito.internal.invocation.Invocation\",\n         \"line\": 55,\n         \"column\": 13\n      },\n      {\n         \"message\": \"Missing import statement for org.mockito.internal.invocation.Invocation\",\n         \"line\": 66,\n         \"column\": 13\n      },\n      {\n         \"message\": \"Missing import statement for org.mockito.internal.invocation.Invocation\",\n         \"line\": 77,\n         \"column\": 13\n      },\n      {\n         \"message\": \"Missing import statement for org.mockito.internal.invocation.Invocation\",\n         \"line\": 88,\n         \"column\": 13\n      },\n      {\n         \"message\": \"Missing import statement for org.mockito.internal.invocation.Invocation\",\n         \"line\": 99,\n         \"column\": 13\n      },\n      {\n         \"message\": \"Missing import statement for org.mockito.internal.invocation.Invocation\",\n         \"line\": 110,\n         \"column\": 13\n      },\n      {\n         \"message\": \"Missing import statement for org.mockito.internal.invocation.Invocation\",\n         \"line\": 121,\n         \"column\": 13\n      },\n      {\n         \"message\": \"Missing import statement for org.mockito.internal.invocation.Invocation\",\n         \"line\": 132,\n         \"column\": 13\n      },\n      {\n         \"message\": \"Missing import statement for org.mockito.internal.invocation.Invocation\",\n         \"line\": 143,\n         \"column\": 13\n      },\n      {\n         \"message\": \"Missing import statement for org.mockito.internal.invocation.Invocation\",\n         \"line\": 154,\n         \"column\": 13\n      },\n      {\n         \"message\": \"Missing import statement for org.mockito.internal.invocation.Invocation\",\n         \"line\": 165,\n         \"column\": 13\n      },\n      {\n         \"message\": \"Missing import statement for org.mockito.internal.invocation.Invocation\",\n         \"line\": 176,\n         \"column\": 13\n      },\n      {\n         \"message\": \"Missing import statement for org.mockito.internal.invocation.Invocation\",\n         \"line\": 187,\n         \"column\": 13\n      },\n      {\n         \"message\": \"Missing import statement for org.mockito.internal.invocation.Invocation\",\n         \"line\": 198,\n         \"column\": 13\n      },\n      {\n         \"message\": \"Missing import statement for org.mockito.internal.invocation.Invocation\",\n         \"line\": 209,\n         \"column\": 13\n      },\n      {\n         \"message\": \"Missing import statement for org.mockito.internal.invocation.Invocation\",\n         \"line\": 220,\n         \"column\": 13\n      },\n      {\n         \"message\": \"Missing import statement for org.mockito.internal.invocation.Invocation\",\n         \"line\": 231,\n         \"column\": 13\n      },\n      {\n         \"message\": \"Missing import statement for org.mockito.internal.invocation.Invocation\",\n         \"line\": 242,\n         \"column\": 13\n      },\n      {\n         \"message\": \"Missing import statement for org.mockito.internal.invocation.Invocation\",\n         \"line\": 253,\n         \"column\": 13\n      },\n      {\n         \"message\": \"Missing import statement for org.mockito.internal.invocation.Invocation\",\n         \"line\": 264,\n         \"column\": 13\n      },\n      {\n         \"message\": \"Missing import statement for org.mockito.internal.invocation.Invocation\",\n         \"line\": 275,\n         \"column\": 13\n      },\n      {\n         \"message\": \"Missing import statement for org.mockito.internal.invocation.Invocation\",\n         \"line\": 286,\n         \"column\": 13\n      },\n      {\n         \"message\": \"Missing import statement for org.mockito.internal.invocation.Invocation\",\n         \"line\": 297,\n         \"column\": 13\n      },\n      {\n         \"message\": \"Missing import statement for org.mockito.internal.invocation.Invocation\",\n         \"line\": 308,\n         \"column\": 13\n      },\n      {\n         \"message\": \"Missing import statement for org.mockito.internal.invocation.Invocation\",\n         \"line\": 319,\n         \"column\": 13\n      },\n      {\n         \"message\": \"Missing import statement for org.mockito.internal.invocation.Invocation\",\n         \"line\": 330,\n         \"column\": 13\n      },\n      {\n         \"message\": \"Missing import statement for org.mockito.internal.invocation.Invocation\",\n         \"line\": 341,\n         \"column\": 13\n      },\n      {\n         \"message\": \"Missing import statement for org.mockito.internal.invocation.Invocation\",\n         \"line\": 352,\n         \"column\": 13\n      },\n      {\n         \"message\": \"Missing import statement for org.mockito.internal.invocation.Invocation\",\n         \"line\": 363,\n         \"column\": 13\n      },\n      {\n         \"message\": \"Missing import statement for org.mockito.internal.invocation.Invocation\",\n         \"line\": 374,\n         \"column\": 13\n      },\n      {\n         \"message\": \"Missing import statement for org.mockito.internal.invocation.Invocation\",\n         \"line\": 385,\n         \"column\": 13\n      },\n      {\n         \"message\": \"Missing import statement for org.mockito.internal.invocation.Invocation\",\n         \"line\": 396,\n         \"column\": 13\n      },\n      {\n         \"message\": \"Missing import statement for org.mockito.internal.invocation.Invocation\",\n         \"line\": 407,\n         \"column\": 13\n      },\n      {\n         \"message\": \"Missing import statement for org.mockito.internal.invocation.Invocation\",\n         \"line\": 418,\n         \"column\": 13\n      },\n      {\n         \"message\": \"Missing import statement for org.mockito.internal.invocation.Invocation\",\n         \"line\": 429,\n         \"column\": 13\n      },\n      {\n         \"message\": \"Missing import statement for org.mockito.internal.invocation.Invocation\",\n         \"line\": 440,\n         \"column\": 13\n      },\n      {\n         \"message\": \"Missing import statement for org.mockito.internal.invocation.Invocation\",\n         \"line\": 451,\n         \"column\": 13\n      },\n      {\n         \"message\": \"Missing import statement for org.mockito.internal.invocation.Invocation\",\n         \"line\": 462,\n         \"column\": 13\n      },\n      {\n         \"message\": \"Missing import statement for org.mockito.internal.invocation.Invocation\",\n         \"line\": 473,\n         \"column\": 13\n      },\n      {\n         \"message\": \"Missing import statement for org.mockito.internal.invocation.Invocation\",\n         \"line\": 484,\n         \"column\": 13\n      },\n      {\n         \"message\": \"Missing import statement for org.mockito.internal.invocation.Invocation\",\n         \"line\": 495,\n         \"column\": 13\n      },\n      {\n         \"message\": \"Missing import statement for org.mockito.internal.invocation.Invocation\",\n         \"line\": 506,\n         \"column\": 13\n      },\n      {\n         \"message\": \"Missing import statement for org.mockito.internal.invocation.Invocation\",\n         \"line\": 517,\n         \"column\": 13\n      },\n      {\n         \"message\": \"Missing import statement for org.mockito.internal.invocation.Invocation\",\n         \"line\": 528,\n         \"column\": 13\n      },\n      {\n         \"message\": \"Missing import statement for org.mockito.internal.invocation.Invocation\",\n         \"line\": 539,\n         \"column\": 13\n      },\n      {\n         \"message\": \"Missing import statement for org.mockito.internal.invocation.Invocation\",\n         \"line\": 550,\n         \"column\": 13\n      },\n      {\n         \"message\": \"Missing import statement for org.mockito.internal.invocation.Invocation\",\n         \"line\": 561,\n         \"column\": 13\n      },\n      {\n         \"message\": \"Missing import statement for org.mockito.internal.invocation.Invocation\",\n         \"line\": 572,\n         \"column\": 13\n      },\n      {\n         \"message\": \"Missing import statement for org.mockito.internal.invocation.Invocation\",\n         \"line\": 583,\n         \"column\": 13\n      },\n      {\n         \"message\": \"Missing import statement for org.mockito.internal.invocation.Invocation\",\n         \"line\": 594,\n         \"column\": 13\n      },\n      {\n         \"message\": \"Missing import statement for org.mockito.internal.invocation.Invocation\",\n         \"line\": 605,\n         \"column\": 13\n      },\n      {\n         \"message\": \"Missing import statement for org.mockito.internal.invocation.Invocation\",\n         \"line\": 616,\n         \"column\": 13\n      },\n      {\n         \"message\": \"Missing import statement for org.mockito.internal.invocation.Invocation\",\n         \"line\": 627,\n         \"column\": 13\n      },\n      {\n         \"message\": \"Missing import statement for org.mockito.internal.invocation.Invocation\",\n         \"line\": 638,\n         \"column\": 13\n      },\n      {\n         \"message\": \"Missing import statement for org.mockito.internal.invocation.Invocation\",\n         \"line\": 649,\n         \"column\": 13\n      },\n      {\n         \"message\": \"Missing import statement for org.mockito.internal.invocation.Invocation\",\n         \"line\": 660,\n         \"column\": 13\n      },\n      {\n         \"message\": \"Missing import statement for org.mockito.internal.invocation.Invocation\",\n         \"line\": 671,\n         \"column\": 13\n      },\n      {\n         \"message\": \"Missing import statement for org.mockito.internal.invocation.Invocation\",\n         \"line\": 682,\n         \"column\": 13\n      },\n      {\n         \"message\": \"Missing import statement for org.mockito.internal.invocation.Invocation\",\n         \"line\": 693,\n         \"column\": 13\n      },\n      {\n         \"message\": \"Missing import statement for org.mockito.internal.invocation.Invocation\",\n         \"line\": 704,\n         \"column\": 13\n      },\n      {\n         \"message\": \"Missing import statement for org.mockito.internal.invocation.Invocation\",\n         \"line\": 715,\n         \"column\": 13\n      },\n      {\n         \"message\": \"Missing import statement for org.mockito.internal.invocation.Invocation\",\n         \"line\": 726,\n         \"column\": 13\n      },\n      {\n         \"message\": \"Missing import statement for org.mockito.internal.invocation.Invocation\",\n         \"line\": 737,\n         \"column\": 13\n      },\n      {\n         \"message\": \"Missing import statement for org.mockito.internal.invocation.Invocation\",\n         \"line\": 748,\n         \"column\": 13\n      },\n      {\n         \"message\": \"Missing import statement for org.mockito.internal.invocation.Invocation\",\n         \"line\": 759,\n         \"column\": 13\n      },\n      {\n         \"message\": \"Missing import statement for org.mockito.internal.invocation.Invocation\",\n         \"line\": 770,\n         \"column\": 13\n      },\n      {\n         \"message\": \"Missing import statement for org.mockito.internal.invocation.Invocation\",\n         \"line\": 781,\n         \"column\": 13\n      },\n      {\n         \"message\": \"Missing import statement for org.mockito.internal.invocation.Invocation\",\n         \"line\": 792,\n         \"column\": 13\n      },\n      {\n         \"message\": \"Missing import statement for org.mockito.internal.invocation.Invocation\",\n         \"line\": 803,\n         \"column\": 13\n      },\n      {\n         \"message\": \"Missing import statement for org.mockito.internal.invocation.Invocation\",\n         \"line\": 814,\n         \"column\": 13\n      },\n      {\n         \"message\": \"Missing import statement for org.mockito.internal.invocation.Invocation\",\n         \"line\": 825,\n         \"column\": 13\n      },\n      {\n         \"message\": \"Missing import statement for org.mockito.internal.invocation.Invocation\",\n         \"line\": 836,\n         \"column\": 13\n      },\n      {\n         \"message\": \"Missing import statement for org.mockito.internal.invocation.Invocation\",\n         \"line\": 847,\n         \"column\": 13\n      },\n      {\n         \"message\": \"Missing import statement for org.mockito.internal.invocation.Invocation\",\n         \"line\": 858,\n         \"column\": 13\n      },\n      {\n         \"message\": \"Missing import statement for org.mockito.internal.invocation.Invocation\",\n         \"line\": 869,\n         \"column\": 13\n      },\n      {\n         \"message\": \"Missing import statement for org.mockito.internal.invocation.Invocation\",\n         \"line\": 880,\n         \"column\": 13\n      },\n      {\n         \"message\": \"Missing import statement for org.mockito.internal.invocation.Invocation\",\n         \"line\": 891,\n         \"column\": 13\n      },\n      {\n         \"message\": \"Missing import statement for org.mockito.internal.invocation.Invocation\",\n         \"line\": 902,\n         \"column\": 13\n      },\n      {\n         \"message\": \"Missing import statement for org.mockito.internal.invocation.Invocation\",\n         \"line\": 913,\n         \"column\": 13\n      },\n      {\n         \"message\": \"Missing import statement for org.mockito.internal.invocation.Invocation\",\n         \"line\": 924,\n         \"column\": 13\n      },\n      {\n         \"message\": \"Missing import statement for org.mockito.internal.invocation.Invocation\",\n         \"line\": 935,\n         \"column\": 13\n      },\n      {\n         \"message\": \"Missing import statement for org.mockito.internal.invocation.Invocation\",\n         \"line\": 946,\n         \"column\": 13\n      },\n      {\n         \"message\": \"Missing import statement for org.mockito.internal.invocation.Invocation\",\n         \"line\": 957,\n         \"column\": 13\n      },\n      {\n         \"message\": \"Missing import statement for org.mockito.internal.invocation.Invocation\",\n         \"line\": 968,\n         \"column\": 13\n      },\n      {\n         \"message\": \"Missing import statement for org.mockito.internal.invocation.Invocation\",\n         \"line\": 979,\n         \"column\": 13\n      },\n      {\n         \"message\": \"Missing import statement for org.mockito.internal.invocation.Invocation\",\n         \"line\": 990,\n         \"column\": 13\n      },\n      {\n         \"message\": \"Missing import statement for org.mockito.internal.invocation.Invocation\",\n         \"line\": 1001,\n         \"column\": 13\n      },\n      {\n         \"message\": \"Missing import statement for org.mockito.internal.invocation.Invocation\",\n         \"line\": 1012,\n         \"column\": 13\n      },\n      {\n         \"message\": \"Missing import statement for org.mockito.internal.invocation.Invocation\",\n         \"line\": 1023,\n         \"column\": 13\n      },\n      {\n         \"message\": \"Missing import statement for org.mockito.internal.invocation.Invocation\",\n         \"line\": 1034,\n         \"column\": 13\n      },\n      {\n         \"message\": \"Missing import statement for org.mockito.internal.invocation.Invocation\",\n         \"line\": 1045,\n         \"column\": 13\n      },\n      {\n         \"message\": \"Missing import statement for org.mockito.internal.invocation.Invocation\",\n         \"line\": 1056,\n         \"column\": 13\n      },\n      {\n         \"message\": \"Missing import statement for org.mockito.internal.invocation.Invocation\",\n         \"line\": 1067,\n         \"column\": 13\n      },\n      {\n         \"message\": \"Missing import statement for org.mockito.internal.invocation.Invocation\",\n         \"line\": 1078,\n         \"column\": 13\n      },\n      {\n         \"message\": \"Missing import statement for org.mockito.internal.invocation.Invocation\",\n         \"line\": 1089,\n         \"column\": 13\n      },\n      {\n         \"message\": \"Missing import statement for org.mockito.internal.invocation.Invocation\",\n         \"line\": 1100,\n         \"column\": 13\n      },\n      {\n         \"message\": \"Missing import statement for org.mockito.internal.invocation.Invocation\",\n         \"line\": 1111,\n         \"column\": 13\n      },\n      {\n         \"message\": \"Missing import statement for org.mockito.internal.invocation.Invocation\",\n         \"line\": 1122,\n         \"column\": 13\n      },\n      {\n         \"message\": \"Missing import statement for org.mockito.internal.invocation.Invocation\",\n         \"line\": 1133,\n         \"column\": 13\n      },\n      {\n         \"message\": \"Missing import statement for org.mockito.internal.invocation.Invocation\",\n         \"line\": 1144,\n         \"column\": 13\n      },\n      {\n         \"message\": \"Missing import statement for org.mockito.internal.invocation.Invocation\",\n         \"line\": 1155,\n         \"column\": 13\n      },\n      {\n         \"message\": \"Missing import statement for org.mockito.internal.invocation.Invocation\",\n         \"line\": 1166,\n         \"column\": 13\n      },\n      {\n         \"message\": \"Missing import statement for org.mockito.internal.invocation.Invocation\",\n         \"line\": 1177,\n         \"column\": 13\n      },\n      {\n         \"message\": \"Missing import statement for org.mockito.internal.invocation.Invocation\",\n         \"line\": 1188,\n         \"column\": 13\n      },\n      {\n         \"message\": \"Missing import statement for org.mockito.internal.invocation.Invocation\",\n         \"line\": 1199,\n         \"column\": 13\n      },\n      {\n         \"message\": \"Missing import statement for org.mockito.internal.invocation.Invocation\",\n         \"line\": 1210,\n         \"column\": 13\n      },\n      {\n         \"message\": \"Missing import statement for org.mockito.internal.invocation.Invocation\",\n         \"line\": 1221,\n         \"column\": 13\n      },\n      {\n         \"message\": \"Missing import statement for org.mockito.internal.invocation.Invocation\",\n         \"line\": 1232,\n         \"column\": 13\n      },\n      {\n         \"message\": \"Missing import statement for org.mockito.internal.invocation.Invocation\",\n         \"line\": 1243,\n         \"column\": 13\n      },\n      {\n         \"message\": \"Missing import statement for org.mockito.internal.invocation.Invocation\",\n         \"line\": 1254,\n         \"column\": 13\n      },\n      {\n         \"message\": \"Missing import statement for org.mockito.internal.invocation.Invocation\",\n         \"line\": 1265,\n         \"column\": 13\n      },\n      {\n         \"message\": \"Missing import statement for org.mockito.internal.invocation.Invocation\",\n         \"line\": 1276,\n         \"column\": 13\n      },\n      {\n         \"message\": \"Missing import statement for org.mockito.internal.invocation.Invocation\",\n         \"line\": 1287,\n         \"column\": 13\n      },\n      {\n         \"message\": \"Missing import statement for org.mockito.internal.invocation.Invocation\",\n         \"line\": 1298,\n         \"column\": 13\n      },\n      {\n         \"message\": \"Missing import statement for org.mockito.internal.invocation.Invocation\",\n         \"line\": 1309,\n         \"column\": 13\n      },\n      {\n         \"message\": \"Missing import statement for org.mockito.internal.invocation.Invocation\",\n         \"line\": 1320,\n         \"column\": 13\n      },\n      {\n         \"message\": \"Missing import statement for org.mockito.internal.invocation.Invocation\",\n         \"line\": 1331,\n         \"column\": 13\n      },\n      {\n         \"message\": \"Missing import statement for org.mockito.internal.invocation.Invocation\",\n         \"line\": 1342,\n         \"column\": 13\n      },\n      {\n         \"message\": \"Missing import statement for org.mockito.internal.invocation.Invocation\",\n         \"line\": 1353,\n         \"column\": 13\n      },\n      {\n         \"message\": \"Missing import statement for org.mockito.internal.invocation.Invocation\",\n         \"line\": 1364,\n         \"column\": 13\n      },\n      {\n         \"message\": \"Missing import statement for org.mockito.internal.invocation.Invocation\",\n         \"line\": 1375,\n         \"column\": 13\n      },\n      {\n         \"message\": \"Missing import statement for org.mockito.internal.invocation.Invocation\",\n         \"line\": 1386,\n         \"column\": 13\n      },\n      {\n         \"message\": \"Missing import statement for org.mockito.internal.invocation.Invocation\",\n         \"line\": 1397,\n         \"column\": 13\n      },\n      {\n         \"message\": \"Missing import statement for org.mockito.internal.invocation.Invocation\",\n         \"line\": 1408,\n         \"column\": 13\n      },\n      {\n         \"message\": \"Missing import statement for org.mockito.internal.invocation.Invocation\",\n         \"line\": 1419,\n         \"column\": 13\n      },\n      {\n         \"message\": \"Missing import statement for org.mockito.internal.invocation.Invocation\",\n         \"line\": 1430,\n         \"column\": 13\n      },\n      {\n         \"message\": \"Missing import statement for org.mockito.internal.invocation.Invocation\",\n         \"line\": 1441,\n         \"column\": 13\n      },\n      {\n         \"message\": \"Missing import statement for org.mockito.internal.invocation.Invocation\",\n         \"line\": 1452,\n         \"column\": 13\n      },\n      {\n         \"message\": \"Missing import statement for org.mockito.internal.invocation.Invocation\",\n         \"line\": 1463,\n         \"column\": 13\n      },\n      {\n         \"message\": \"Missing import statement for org.mockito.internal.invocation.Invocation\",\n         \"line\": 1474,\n         \"column\": 13\n      },\n      {\n         \"message\": \"Missing import statement for org.mockito.internal.invocation.Invocation\",\n         \"line\": 1485,\n         \"column\": 13\n      },\n      {\n         \"message\": \"Missing import statement for org.mockito.internal.invocation.Invocation\",\n         \"line\": 1496,\n         \"column\": 13\n      },\n      {\n         \"message\": \"Missing import statement for org.mockito.internal.invocation.Invocation\",\n         \"line\": 1507,\n         \"column\": 13\n      },\n      {\n         \"message\": \"Missing import statement for org.mockito.internal.invocation.Invocation\",\n         \"line\": 1518,\n         \"column\": 13\n      },\n      {\n         \"message\": \"Missing import statement for org.mockito.internal.invocation.Invocation\",\n         \"line\": 1529,\n         \"column\": 13\n      },\n      {\n         \"message\": \"Missing import statement for org.mockito.internal.invocation.Invocation\",\n         \"line\": 1540,\n         \"column\": 13\n      },\n      {\n         \"message\": \"Missing import statement for org.mockito.internal.invocation.Invocation\",\n         \"line\": 1551,\n         \"column\": 13\n      },\n      {\n         \"message\": \"Missing import statement for org.mockito.internal.invocation.Invocation\",\n         \"line\": 1562,\n         \"column\": 13\n      },\n      {\n         \"message\": \"Missing import statement for org.mockito.internal.invocation.Invocation\",\n         \"line\": 1573,\n         \"column\": 13\n      },\n      {\n         \"message\": \"Missing import statement for org.mockito.internal.invocation.Invocation\",\n         \"line\": 1584,\n         \"column\": 13\n      },\n      {\n         \"message\": \"Missing import statement for org.mockito.internal.invocation.Invocation\",\n         \"line\": 1595,\n         \"column\": 13\n      },\n      {\n         \"message\": \"Missing import statement for org.mockito.internal.invocation.Invocation\",\n         \"line\": 1606,\n         \"column\": 13\n      },\n      {\n         \"message\": \"Missing import statement for org.mockito.internal.invocation.Invocation\",\n         \"line\": 1617,\n         \"column\": 13\n      },\n      {\n         \"message\": \"Missing import statement for org.mockito.internal.invocation.Invocation\",\n         \"line\": 1628,\n         \"column\": 13\n      },\n      {\n         \"message\": \"Missing import statement for org.mockito.internal.invocation.Invocation\",\n         \"line\": 1639,\n         \"column\": 13\n      },\n      {\n         \"message\": \"Missing import statement for org.mockito.internal.invocation.Invocation\",\n         \"line\": 1650,\n         \"column\": 13\n      },\n      {\n         \"message\": \"Missing import statement for org.mockito.internal.invocation.Invocation\",\n         \"line\": 1661,\n         \"column\": 13\n      },\n      {\n         \"message\": \"Missing import statement for org.mockito.internal.invocation.Invocation\",\n         \"line\": 1672,\n         \"column\": 13\n      },\n      {\n         \"message\": \"Missing import statement for org.mockito.internal.invocation.Invocation\",\n         \"line\": 1683,\n         \"column\": 13\n      },\n      {\n         \"message\": \"Missing import statement for org.mockito.internal.invocation.Invocation\",\n         \"line\": 1694,\n         \"column\": 13\n      },\n      {\n         \"message\": \"Missing import statement for org.mockito.internal.invocation.Invocation\",\n         \"line\": 1705,\n         \"column\": 13\n      },\n      {\n         \"message\": \"Missing import statement for org.mockito.internal.invocation.Invocation\",\n         \"line\": 1716,\n         \"column\": 13\n      },\n      {\n         \"message\": \"Missing import statement for org.mockito.internal.invocation.Invocation\",\n         \"line\": 1727,\n         \"column\": 13\n      },\n      {\n         \"message\": \"Missing import statement for org.mockito.internal.invocation.Invocation\",\n         \"line\": 1738,\n         \"column\": 13\n      },\n      {\n         \"message\": \"Missing import statement for org.mockito.internal.invocation.Invocation\",\n         \"line\": 1749,\n         \"column\": 13\n      },\n      {\n         \"message\": \"Missing import statement for org.mockito.internal.invocation.Invocation\",\n         \"line\": 1760,\n         \"column\": 13\n      },\n      {\n         \"message\": \"Missing import statement for org.mockito.internal.invocation.Invocation\",\n         \"line\": 1771,\n         \"column\": 13\n      },\n      {\n         \"message\": \"Missing import statement for org.mockito.internal.invocation.Invocation\",\n         \"line\": 1782,\n         \"column\": 13\n      },\n      {\n         \"message\": \"Missing import statement for org.mockito.internal.invocation.Invocation\",\n         \"line\": 1793,\n         \"column\": 13\n      },\n      {\n         \"message\": \"Missing import statement for org.mockito.internal.invocation.Invocation\",\n         \"line\": 1804,\n         \"column\": 13\n      },\n      {\n         \"message\": \"Missing import statement for org.mockito.internal.invocation.Invocation\",\n         \"line\": 1815,\n         \"column\": 13\n      },\n      {\n         \"message\": \"Missing import statement for org.mockito.internal.invocation.Invocation\",\n         \"line\": 1826,\n         \"column\": 13\n      },\n      {\n         \"message\": \"Missing import statement for org.mockito.internal.invocation.Invocation\",\n         \"line\": 1837,\n         \"column\": 13\n      },\n      {\n         \"message\": \"Missing import statement for org.mockito.internal.invocation.Invocation\",\n         \"line\": 1848,\n         \"column\": 13\n      },\n      {\n         \"message\": \"Missing import statement for org.mockito.internal.invocation.Invocation\",\n         \"line\": 1859,\n         \"column\": 13\n      },\n      {\n         \"message\": \"Missing import statement for org.mockito.internal.invocation.Invocation\",\n         \"line\": 1870,\n         \"column\": 13\n      },\n      {\n         \"message\": \"Missing import statement for org.mockito.internal.invocation.Invocation\",\n         \"line\": 1881,\n         \"column\": 13\n      },\n      {\n         \"message\": \"Missing import statement for org.mockito.internal.invocation.Invocation\",\n         \"line\": 1892,\n         \"column\": 13\n      },\n      {\n         \"message\": \"Missing import statement for org.mockito.internal.invocation.Invocation\",\n         \"line\": 1903,\n         \"column\": 13\n      },\n      {\n         \"message\": \"Missing import statement for org.mockito.internal.invocation.Invocation\",\n         \"line\": 1914,\n         \"column\": 13\n      },\n      {\n         \"message\": \"Missing import statement for org.mockito.internal.invocation.Invocation\",\n         \"line\": 1925,\n         \"column\": 13\n      },\n      {\n         \"message\": \"Missing import statement for org.mockito.internal.invocation.Invocation\",\n         \"line\": 1936,\n         \"column\": 13\n      },\n      {\n         \"message\": \"Missing import statement for org.mockito.internal.invocation.Invocation\",\n         \"line\": 1947,\n         \"column\": 13\n      },\n      {\n         \"message\": \"Missing import statement for org.mockito.internal.invocation.Invocation\",\n         \"line\": 1958,\n         \"column\": 13\n      },\n      {\n         \"message\": \"Missing import statement for org.mockito.internal.invocation.Invocation\",\n         \"line\": 1969,\n         \"column\": 13\n      },\n      {\n         \"message\": \"Missing import statement for org.mockito.internal.invocation.Invocation\",\n         \"line\": 1980,\n         \"column\": 13\n      },\n      {\n         \"message\": \"Missing import statement for org.mockito.internal.invocation.Invocation\",\n         \"line\": 1991,\n         \"column\": 13\n      },\n      {\n         \"message\": \"Missing import statement for org.mockito.internal.invocation.Invocation\",\n         \"line\": 2002,\n         \"column\": 13\n      },\n      {\n         \"message\": \"Missing import statement for org.mockito.internal.invocation.Invocation\",\n         \"line\": 2013,\n         \"column\": 13\n      },\n      {\n         \"message\": \"Missing import statement for org.mockito.internal.invocation.Invocation\",\n         \"line\": 2024,\n         \"column\": 13\n      },\n      {\n         \"message\": \"Missing import statement for org.mockito.internal.invocation.Invocation\",\n         \"line\": 2035,\n         \"column\": 13\n      },\n      {\n         \"message\": \"Missing import statement for org.mockito.internal.invocation.Invocation\",\n         \"line\": 2046,\n         \"column\": 13\n      },\n      {\n         \"message\": \"Missing import statement for org.mockito.internal.invocation.Invocation\",\n         \"line\": 2057,\n         \"column\": 13\n      },\n      {\n         \"message\": \"Missing import statement for org.mockito.internal.invocation.Invocation\",\n         \"line\": 2068,\n         \"column\": 13\n      },\n      {\n         \"message\": \"Missing import statement for org.mockito.internal.invocation.Invocation\",\n         \"line\": 2079,\n         \"column\": 13\n      },\n      {\n         \"message\": \"Missing import statement for org.mockito.internal.invocation.Invocation\",\n         \"line\": 2090,\n         \"column\": 13\n      },\n      {\n         \"message\": \"Missing import statement for org.mockito.internal.invocation.Invocation\",\n         \"line\": 2101,\n         \"column\": 13\n      },\n      {\n         \"message\": \"Missing import statement for org.mockito.internal.invocation.Invocation\",\n         \"line\": 2112,\n         \"column\": 13\n      },\n      {\n         \"message\": \"Missing import statement for org.mockito.internal.invocation.Invocation\",\n         \"line\": 2123,\n         \"column\": 13\n      },\n      {\n         \"message\": \"Missing import statement for org.mockito.internal.invocation.Invocation\",\n         \"line\": 2134,\n         \"column\": 13\n      },\n      {\n         \"message\": \"Missing import statement for org.mockito.internal.invocation.Invocation\",\n         \"line\": 2145,\n         \"column\": 13\n      },\n      {\n         \"message\": \"Missing import statement for org.mockito.internal.invocation.Invocation\",\n         \"line\": 2156,\n         \"column\": 13\n      },\n      {\n         \"message\": \"Missing import statement for org.mockito.internal.invocation.Invocation\",\n         \"line\": 2167,\n         \"column\": 13\n      },\n      {\n         \"message\": \"Missing import statement for org.mockito.internal.invocation.Invocation\",\n         \"line\": 2178,\n         \"column\": 13\n      },\n      {\n         \"message\": \"Missing import statement for org.mockito.internal.invocation.Invocation\",\n         \"line\": 2190,\n         \"column\": 13\n      },\n      {\n         \"message\": \"Missing import statement for org.mockito.internal.invocation.Invocation\",\n         \"line\": 2201,\n         \"column\": 13\n      },\n      {\n         \"message\": \"Missing import statement for org.mockito.internal.invocation.Invocation\",\n         \"line\": 2212,\n         \"column\": 13\n      },\n      {\n         \"message\": \"Missing import statement for org.mockito.internal.invocation.Invocation\",\n         \"line\": 2223,\n         \"column\": 13\n      },\n      {\n         \"message\": \"Missing import statement for org.mockito.internal.invocation.Invocation\",\n         \"line\": 2234,\n         \"column\": 13\n      },\n      {\n         \"message\": \"Missing import statement for org.mockito.internal.invocation.Invocation\",\n         \"line\": 2245,\n         \"column\": 13\n      },\n      {\n         \"message\": \"Missing import statement for org.mockito.internal.invocation.Invocation\",\n         \"line\": 2256,\n         \"column\": 13\n      },\n      {\n         \"message\": \"Missing import statement for org.mockito.internal.invocation.Invocation\",\n         \"line\": 2267,\n         \"column\": 13\n      },\n      {\n         \"message\": \"Missing import statement for org.mockito.internal.invocation.Invocation\",\n         \"line\": 2278,\n         \"column\": 13\n      },\n      {\n         \"message\": \"Missing import statement for org.mockito.internal.invocation.Invocation\",\n         \"line\": 2289,\n         \"column\": 13\n      },\n      {\n         \"message\": \"Missing import statement for org.mockito.internal.invocation.Invocation\",\n         \"line\": 2300,\n         \"column\": 13\n      },\n      {\n         \"message\": \"Missing import statement for org.mockito.internal.invocation.Invocation\",\n         \"line\": 2311,\n         \"column\": 13\n      },\n      {\n         \"message\": \"Missing import statement for org.mockito.internal.invocation.Invocation\",\n         \"line\": 2322,\n         \"column\": 13\n      },\n      {\n         \"message\": \"Missing import statement for org.mockito.internal.invocation.Invocation\",\n         \"line\": 2333,\n         \"column\": 13\n      },\n      {\n         \"message\": \"Missing import statement for org.mockito.internal.invocation.Invocation\",\n         \"line\": 2344,\n         \"column\": 13\n      },\n      {\n         \"message\": \"Missing import statement for org.mockito.internal.invocation.Invocation\",\n         \"line\": 2355,\n         \"column\": 13\n      },\n      {\n         \"message\": \"Missing import statement for org.mockito.internal.invocation.Invocation\",\n         \"line\": 2366,\n         \"column\": 13\n      },\n      {\n         \"message\": \"Missing import statement for org.mockito.internal.invocation.Invocation\",\n         \"line\": 2377,\n         \"column\": 13\n      },\n      {\n         \"message\": \"Missing import statement for org.mockito.internal.invocation.Invocation\",\n         \"line\": 2388,\n         \"column\": 13\n      },\n      {\n         \"message\": \"Missing import statement for org.mockito.internal.invocation.Invocation\",\n         \"line\": 2399,\n         \"column\": 13\n      },\n      {\n         \"message\": \"Missing import statement for org.mockito.internal.invocation.Invocation\",\n         \"line\": 2410,\n         \"column\": 13\n      },\n      {\n         \"message\": \"Missing import statement for org.mockito.internal.invocation.Invocation\",\n         \"line\": 2421,\n         \"column\": 13\n      },\n      {\n         \"message\": \"Missing import statement for org.mockito.internal.invocation.Invocation\",\n         \"line\": 2432,\n         \"column\": 13\n      },\n      {\n         \"message\": \"Missing import statement for org.mockito.internal.invocation.Invocation\",\n         \"line\": 2443,\n         \"column\": 13\n      },\n      {\n         \"message\": \"Missing import statement for org.mockito.internal.invocation.Invocation\",\n         \"line\": 2454,\n         \"column\": 13\n      },\n      {\n         \"message\": \"Missing import statement for org.mockito.internal.invocation.Invocation\",\n         \"line\": 2465,\n         \"column\": 13\n      },\n      {\n         \"message\": \"Missing import statement for org.mockito.internal.invocation.Invocation\",\n         \"line\": 2476,\n         \"column\": 13\n      },\n      {\n         \"message\": \"Missing import statement for org.mockito.internal.invocation.Invocation\",\n         \"line\": 2487,\n         \"column\": 13\n      },\n      {\n         \"message\": \"Missing import statement for org.mockito.internal.invocation.Invocation\",\n         \"line\": 2498,\n         \"column\": 13\n      },\n      {\n         \"message\": \"Missing import statement for org.mockito.internal.invocation.Invocation\",\n         \"line\": 2509,\n         \"column\": 13\n      },\n      {\n         \"message\": \"Missing import statement for org.mockito.internal.invocation.Invocation\",\n         \"line\": 2520,\n         \"column\": 13\n      },\n      {\n         \"message\": \"Missing import statement for org.mockito.internal.invocation.Invocation\",\n         \"line\": 2531,\n         \"column\": 13\n      }]}"}}